vnet_manager/__init__.py
vnet_manager/argeparser.py
vnet_manager/conf.py
vnet_manager/log.py
vnet_manager/vnet_manager.py
vnet_manager/actions/__init__.py
vnet_manager/actions/manager.py
vnet_manager/config/__init__.py
vnet_manager/config/config.py
vnet_manager/config/validate.py
vnet_manager/environment/__init__.py
vnet_manager/environment/host.py
vnet_manager/environment/lxc.py
vnet_manager/operations/__init__.py
vnet_manager/operations/files.py
vnet_manager/operations/image.py
vnet_manager/operations/interface.py
vnet_manager/operations/machine.py
vnet_manager/operations/profile.py
vnet_manager/operations/storage.py
vnet_manager/providers/__init__.py
vnet_manager/providers/lxc.py
vnet_manager/settings/__init__.py
vnet_manager/settings/base.py
vnet_manager/settings/test.py
vnet_manager/utils/__init__.py
vnet_manager/utils/files.py
vnet_manager/utils/mac.py
vnet_manager/utils/user.py
vnet_manager/utils/version.py
vnet_manager/utils/logging/__init__.py
vnet_manager/utils/logging/formatters.py
vnet_manager-1.1.1.dist-info/LICENSE
vnet_manager-1.1.1.dist-info/METADATA
vnet_manager-1.1.1.dist-info/WHEEL
vnet_manager-1.1.1.dist-info/entry_points.txt
vnet_manager-1.1.1.dist-info/top_level.txt
vnet_manager-1.1.1.dist-info/RECORD
